LICENSE
MANIFEST.in
README.rst
setup.cfg
setup.py
django_signals_cloudevents/__init__.py
django_signals_cloudevents/settings.py
django_signals_cloudevents/tests.py
django_signals_cloudevents.egg-info/PKG-INFO
django_signals_cloudevents.egg-info/SOURCES.txt
django_signals_cloudevents.egg-info/dependency_links.txt
django_signals_cloudevents.egg-info/requires.txt
django_signals_cloudevents.egg-info/top_level.txt