Metadata-Version: 2.1
Name: django-signals-cloudevents
Version: 0.1.2
Summary: App to produce Cloudevents from Django model signals
Home-page: https://github.com/airspot-dev/django-signals-cloudevents
Author: Airspot S.r.l.
Author-email: info@airspot.tech
License: BSD-3-Clause  # Example license
Keywords: cloudevents knative eventing krules
Platform: UNKNOWN
Classifier: Programming Language :: Python :: 3
Classifier: Operating System :: OS Independent
Classifier: Framework :: Django
Requires-Python: >=3.6
